cloe_nessy/__init__.py
cloe_nessy/py.typed
cloe_nessy/clients/__init__.py
cloe_nessy/clients/api_client/__init__.py
cloe_nessy/clients/api_client/api_client.py
cloe_nessy/clients/api_client/api_response.py
cloe_nessy/clients/api_client/auth.py
cloe_nessy/clients/api_client/exceptions.py
cloe_nessy/clients/api_client/pagination_config.py
cloe_nessy/clients/api_client/pagination_strategy.py
cloe_nessy/file_utilities/__init__.py
cloe_nessy/file_utilities/exceptions.py
cloe_nessy/file_utilities/factory.py
cloe_nessy/file_utilities/get_file_paths.py
cloe_nessy/file_utilities/location_types.py
cloe_nessy/file_utilities/strategies/__init__.py
cloe_nessy/file_utilities/strategies/base_strategy.py
cloe_nessy/file_utilities/strategies/local_strategy.py
cloe_nessy/file_utilities/strategies/onelake_strategy.py
cloe_nessy/file_utilities/strategies/utils_strategy.py
cloe_nessy/integration/__init__.py
cloe_nessy/integration/delta_loader/__init__.py
cloe_nessy/integration/delta_loader/delta_load_options.py
cloe_nessy/integration/delta_loader/delta_loader.py
cloe_nessy/integration/delta_loader/delta_loader_factory.py
cloe_nessy/integration/delta_loader/delta_loader_metadata_table.py
cloe_nessy/integration/delta_loader/strategies/__init__.py
cloe_nessy/integration/delta_loader/strategies/delta_cdf_loader.py
cloe_nessy/integration/delta_loader/strategies/delta_timestamp_loader.py
cloe_nessy/integration/reader/__init__.py
cloe_nessy/integration/reader/api_reader.py
cloe_nessy/integration/reader/catalog_reader.py
cloe_nessy/integration/reader/excel_reader.py
cloe_nessy/integration/reader/exceptions.py
cloe_nessy/integration/reader/file_reader.py
cloe_nessy/integration/reader/reader.py
cloe_nessy/integration/writer/__init__.py
cloe_nessy/integration/writer/catalog_writer.py
cloe_nessy/integration/writer/file_writer.py
cloe_nessy/integration/writer/writer.py
cloe_nessy/integration/writer/delta_writer/__init__.py
cloe_nessy/integration/writer/delta_writer/delta_append_writer.py
cloe_nessy-1.0.3.dist-info/METADATA
cloe_nessy-1.0.3.dist-info/WHEEL
cloe_nessy-1.0.3.dist-info/RECORD
