Metadata-Version: 2.4
Name: cloe-nessy
Version: 1.0.3
Summary: Your friendly datalake monster.
Project-URL: homepage, https://initions.com/
Author-email: initions <ICSMC_EXT_PYPIORG@accenture.com>
License: MIT
Classifier: Development Status :: 5 - Production/Stable
Classifier: Environment :: Console
Classifier: Intended Audience :: Developers
Classifier: License :: OSI Approved :: MIT License
Classifier: Operating System :: OS Independent
Classifier: Programming Language :: Python :: 3
Classifier: Topic :: Database
Requires-Python: <3.14,>=3.11
Requires-Dist: azure-identity<2.0.0,>=1.19.0
Requires-Dist: cloe-logging[databricks,log-analytics]<0.4,>=0.3.8
Requires-Dist: databricks-sdk<1.0.0,>=0.36.0
Requires-Dist: fsspec<2025.12.1,>=2025.12.0
Requires-Dist: httpx<1.0.0,>=0.27.2
Requires-Dist: jinja2<4.0.0,>=3.1.4
Requires-Dist: matplotlib<4.0.0,>=3.9.2
Requires-Dist: networkx<4.0,>=3.3
Requires-Dist: openpyxl<4.0.0,>=3.1.5
Requires-Dist: pandas-stubs<3.0.0.0,>=2.2.2.240807
Requires-Dist: pydantic-settings<3.0.0,>=2.4.0
Requires-Dist: pydantic<3.0.0,>=2.7.2
Requires-Dist: pyyaml<7.0.0,>=6.0.1
Requires-Dist: requests<3.0.0,>=2.32.3
Requires-Dist: types-networkx<4.0.0.0,>=3.2.1.20240820
Requires-Dist: types-pyyaml<7.0.0.0,>=6.0.12.20240311
Requires-Dist: types-requests<3.0.0.0,>=2.32.0.20240712
